pyitd/__init__.py
pyitd/boundary_conditions.py
pyitd/common.py
pyitd/extr.py
pyitd/extrema_1.py
pyitd/itd.py
snowland_itd-0.0.1.dist-info/DESCRIPTION.rst
snowland_itd-0.0.1.dist-info/METADATA
snowland_itd-0.0.1.dist-info/RECORD
snowland_itd-0.0.1.dist-info/WHEEL
snowland_itd-0.0.1.dist-info/metadata.json
snowland_itd-0.0.1.dist-info/top_level.txt
